__init__.py
piwebapi/__init__.py
piwebapi/api_client.py
piwebapi/pi_web_api_client.py
piwebapi/rest.py
piwebapi/api/__init__.py
piwebapi/api/analysis_api.py
piwebapi/api/analysis_category_api.py
piwebapi/api/analysis_rule_api.py
piwebapi/api/analysis_rule_plug_in_api.py
piwebapi/api/analysis_template_api.py
piwebapi/api/asset_database_api.py
piwebapi/api/asset_server_api.py
piwebapi/api/attribute_api.py
piwebapi/api/attribute_category_api.py
piwebapi/api/attribute_template_api.py
piwebapi/api/attribute_trait_api.py
piwebapi/api/batch_api.py
piwebapi/api/calculation_api.py
piwebapi/api/channel_api.py
piwebapi/api/configuration_api.py
piwebapi/api/data_api.py
piwebapi/api/data_server_api.py
piwebapi/api/element_api.py
piwebapi/api/element_category_api.py
piwebapi/api/element_template_api.py
piwebapi/api/enumeration_set_api.py
piwebapi/api/enumeration_value_api.py
piwebapi/api/event_frame_api.py
piwebapi/api/home_api.py
piwebapi/api/point_api.py
piwebapi/api/security_identity_api.py
piwebapi/api/security_mapping_api.py
piwebapi/api/stream_api.py
piwebapi/api/stream_set_api.py
piwebapi/api/system_api.py
piwebapi/api/table_api.py
piwebapi/api/table_category_api.py
piwebapi/api/time_rule_api.py
piwebapi/api/time_rule_plug_in_api.py
piwebapi/api/unit_api.py
piwebapi/api/unit_class_api.py
piwebapi/models/__init__.py
piwebapi/models/pi_analysis.py
piwebapi/models/pi_analysis_category.py
piwebapi/models/pi_analysis_category_links.py
piwebapi/models/pi_analysis_links.py
piwebapi/models/pi_analysis_rule.py
piwebapi/models/pi_analysis_rule_links.py
piwebapi/models/pi_analysis_rule_plug_in.py
piwebapi/models/pi_analysis_rule_plug_in_links.py
piwebapi/models/pi_analysis_template.py
piwebapi/models/pi_analysis_template_links.py
piwebapi/models/pi_annotation.py
piwebapi/models/pi_annotation_links.py
piwebapi/models/pi_asset_database.py
piwebapi/models/pi_asset_database_links.py
piwebapi/models/pi_asset_server.py
piwebapi/models/pi_asset_server_links.py
piwebapi_restapi-0.0.6.dist-info/LICENSE.md
piwebapi_restapi-0.0.6.dist-info/METADATA
piwebapi_restapi-0.0.6.dist-info/WHEEL
piwebapi_restapi-0.0.6.dist-info/top_level.txt
piwebapi_restapi-0.0.6.dist-info/RECORD
